DataModelDict/DataModelDict.py
DataModelDict/VERSION
DataModelDict/__init__.py
DataModelDict/joinpath.py
DataModelDict/parsepath.py
DataModelDict/uber_open_rmode.py
DataModelDict-0.9.9.dist-info/LICENSE.TXT
DataModelDict-0.9.9.dist-info/METADATA
DataModelDict-0.9.9.dist-info/WHEEL
DataModelDict-0.9.9.dist-info/top_level.txt
DataModelDict-0.9.9.dist-info/RECORD
