Metadata-Version: 2.1
Name: DataModelDict
Version: 0.9.9
Summary: Class allowing for data models equivalently represented as Python dictionaries, JSON, and XML
Home-page: https://github.com/usnistgov/DataModelDict/
Author: Lucas Hale
Author-email: lucas.hale@nist.gov
License: UNKNOWN
Keywords: json,xml,dictionary
Platform: UNKNOWN
Classifier: Development Status :: 5 - Production/Stable
Classifier: Intended Audience :: Science/Research
Classifier: Natural Language :: English
Classifier: Operating System :: OS Independent
Classifier: Programming Language :: Python :: 3.7
Classifier: Programming Language :: Python :: 3.8
Classifier: Programming Language :: Python :: 3.9
Classifier: Programming Language :: Python :: 3.10
Classifier: Topic :: Text Processing :: Markup :: XML
License-File: LICENSE.TXT
Requires-Dist: xmltodict
